CHANGES.rst
COPYRIGHT.txt
LICENSE.txt
MANIFEST.in
README.rst
buildout.cfg
setup.py
Products/__init__.py
Products.ZNagios.egg-info/PKG-INFO
Products.ZNagios.egg-info/SOURCES.txt
Products.ZNagios.egg-info/dependency_links.txt
Products.ZNagios.egg-info/namespace_packages.txt
Products.ZNagios.egg-info/not-zip-safe
Products.ZNagios.egg-info/requires.txt
Products.ZNagios.egg-info/top_level.txt
Products/ZNagios/__init__.py
Products/ZNagios/check_zope.py
Products/ZNagios/munin_client.py
Products/ZNagios/zcmonitor.py
Products/ZNagios/zcmonitor.zcml
Products/ZNagios/zeo_munin.py
Products/ZNagios/zope.cfg