Metadata-Version: 1.1
Name: Products.ZNagios
Version: 0.7.2
Summary: ZNagios provides the ability for Nagios and munin to tap into the Zope2 server and retrieve status and performance data.
Home-page: http://pypi.python.org/pypi/Products.ZNagios
Author: Zope Corporation and contributors
Author-email: zope-dev@zope.org
License: ZPL
Keywords: Zope Nagios Munin
Platform: UNKNOWN
Classifier: Framework :: Zope2
Classifier: License :: OSI Approved :: Zope Public License
Classifier: Programming Language :: Python
Classifier: Topic :: System :: Monitoring
